LICENSE.md
MANIFEST.in
README.md
pyproject.toml
setup.py
pymzid/__init__.py
pymzid/__main__.py
pymzid/main.py
pymzid/parse_args.py
pymzid/read_mzid.py
pymzid.egg-info/PKG-INFO
pymzid.egg-info/SOURCES.txt
pymzid.egg-info/dependency_links.txt
pymzid.egg-info/entry_points.txt
pymzid.egg-info/requires.txt
pymzid.egg-info/top_level.txt
tests/__init__.py
tests/test_mzid.py
tests/data/comet_percolator/.DS_Store
tests/data/comet_percolator/percolator.target.mzid
tests/data/comet_percolator/percolator.target.psms.txt
tests/data/msgfplus/20180216_BSA.mzid