Metadata-Version: 2.1
Name: pymzid
Version: 0.3.2
Summary: pymzid reads in mzidentml files from proteomics search engine
Home-page: https://github.com/Lau-Lab/pymzid/
Author: Edward Lau
Author-email: edward.lau@cuanschutz.edu
License: UNKNOWN
Project-URL: Source, https://github.com/Lau-Lab/pymzid
Project-URL: Edward Lau Lab, https://www.laulab.net
Keywords: scientific proteomics mass-spectrometry mzid mzidentml
Platform: UNKNOWN
Classifier: Development Status :: 3 - Alpha
Classifier: Intended Audience :: Developers
Classifier: Topic :: Software Development :: Build Tools
Classifier: License :: OSI Approved :: MIT License
Classifier: Programming Language :: Python :: 3.7
Classifier: Programming Language :: Python :: 3.8
Classifier: Programming Language :: Python :: 3 :: Only
Requires-Python: >=3.6, <4
